[
  {
    "title": "Tiger_L7",
    "link_thumb": "https://live.staticflickr.com/65535/51703065462_2f4f7fb099_o.gif",
    "id_album": "2111354123",
    "total": 2,
    "size_max_detail_page": 1,
    "list_detail": [
      {
        "index_page": 0,
        "link_page": "https://github.com/lmbstudiocontact/mb5_dt_alb_0/raw/main/14132021_dta_2111354123_index_0.json"
      }
    ]
  },
  {
    "title": "Donald Duck Cartoon_L3",
    "link_thumb": "https://live.staticflickr.com/65535/51697469899_fe1c43b5f5_o.gif",
    "id_album": "-1917621483",
    "total": 4,
    "size_max_detail_page": 1,
    "list_detail": [
      {
        "index_page": 0,
        "link_page": "https://github.com/lmbstudiocontact/mb5_dt_alb_0/raw/main/14132021_dta_-1917621483_index_0.json"
      }
    ]
  },
  {
    "title": "Death Note Anime_L1",
    "link_thumb": "https://live.staticflickr.com/65535/51697057154_e43141f649_o.gif",
    "id_album": "-374116174",
    "total": 8,
    "size_max_detail_page": 1,
    "list_detail": [
      {
        "index_page": 0,
        "link_page": "https://github.com/lmbstudiocontact/mb5_dt_alb_0/raw/main/14132021_dta_-374116174_index_0.json"
      }
    ]
  },
  {
    "title": "Naruto Anime_L1",
    "link_thumb": "https://live.staticflickr.com/65535/51701676279_991a003d78_o.gif",
    "id_album": "1894397983",
    "total": 37,
    "size_max_detail_page": 1,
    "list_detail": [
      {
        "index_page": 0,
        "link_page": "https://github.com/lmbstudiocontact/mb5_dt_alb_0/raw/main/14132021_dta_1894397983_index_0.json"
      }
    ]
  },
  {
    "title": "Dragon Art_L1",
    "link_thumb": "https://live.staticflickr.com/65535/51696081877_7b5c76182d_o.gif",
    "id_album": "2059013998",
    "total": 13,
    "size_max_detail_page": 1,
    "list_detail": [
      {
        "index_page": 0,
        "link_page": "https://github.com/lmbstudiocontact/mb5_dt_alb_0/raw/main/14132021_dta_2059013998_index_0.json"
      }
    ]
  },
  {
    "title": "Mickey Cartoon_L3",
    "link_thumb": "https://live.staticflickr.com/65535/51700500143_7445979811_o.gif",
    "id_album": "1680949824",
    "total": 22,
    "size_max_detail_page": 1,
    "list_detail": [
      {
        "index_page": 0,
        "link_page": "https://github.com/lmbstudiocontact/mb5_dt_alb_0/raw/main/14132021_dta_1680949824_index_0.json"
      }
    ]
  },
  {
    "title": "Raccoons_L4",
    "link_thumb": "https://live.staticflickr.com/65535/51702499092_ed19d068cf_o.gif",
    "id_album": "1998705267",
    "total": 20,
    "size_max_detail_page": 1,
    "list_detail": [
      {
        "index_page": 0,
        "link_page": "https://github.com/lmbstudiocontact/mb5_dt_alb_0/raw/main/14132021_dta_1998705267_index_0.json"
      }
    ]
  },
  {
    "title": "Death Note Anime_L5",
    "link_thumb": "https://live.staticflickr.com/65535/51697092764_76381e4165_o.gif",
    "id_album": "-374116170",
    "total": 8,
    "size_max_detail_page": 1,
    "list_detail": [
      {
        "index_page": 0,
        "link_page": "https://github.com/lmbstudiocontact/mb5_dt_alb_0/raw/main/14132021_dta_-374116170_index_0.json"
      }
    ]
  },
  {
    "title": "Simpsons Cartoon_L4",
    "link_thumb": "https://live.staticflickr.com/65535/51704637145_6e6d1791ba_o.gif",
    "id_album": "1276946591",
    "total": 8,
    "size_max_detail_page": 1,
    "list_detail": [
      {
        "index_page": 0,
        "link_page": "https://github.com/lmbstudiocontact/mb5_dt_alb_0/raw/main/14132021_dta_1276946591_index_0.json"
      }
    ]
  }
]