[
  {
    "title": "Naruto Anime_L5",
    "link_thumb": "https://live.staticflickr.com/65535/51788114455_4e76683d52_o.gif",
    "id_album": "1894397987",
    "total": 37,
    "size_max_detail_page": 1,
    "list_detail": [
      {
        "index_page": 0,
        "link_page": "https://github.com/lmbstudiocontact/mb5_dt_alb_0/raw/main/14132021_dta_1894397987_index_0.json"
      }
    ]
  },
  {
    "title": "Raccoons_L3",
    "link_thumb": "https://live.staticflickr.com/65535/51788151670_68f2e7f891_o.gif",
    "id_album": "1998705266",
    "total": 20,
    "size_max_detail_page": 1,
    "list_detail": [
      {
        "index_page": 0,
        "link_page": "https://github.com/lmbstudiocontact/mb5_dt_alb_0/raw/main/14132021_dta_1998705266_index_0.json"
      }
    ]
  },
  {
    "title": "Plants Vs Zombies_L1",
    "link_thumb": "https://live.staticflickr.com/65535/51788120345_48e3ed30b9_o.gif",
    "id_album": "-1426777470",
    "total": 24,
    "size_max_detail_page": 1,
    "list_detail": [
      {
        "index_page": 0,
        "link_page": "https://github.com/lmbstudiocontact/mb5_dt_alb_0/raw/main/14132021_dta_-1426777470_index_0.json"
      }
    ]
  },
  {
    "title": "Smurf Houses Cartoon_L3",
    "link_thumb": "https://live.staticflickr.com/65535/51788144025_188dbc8522_o.gif",
    "id_album": "228264852",
    "total": 4,
    "size_max_detail_page": 1,
    "list_detail": [
      {
        "index_page": 0,
        "link_page": "https://github.com/lmbstudiocontact/mb5_dt_alb_0/raw/main/14132021_dta_228264852_index_0.json"
      }
    ]
  },
  {
    "title": "Ratatouille Cartoon_L5",
    "link_thumb": "https://live.staticflickr.com/65535/51788167325_3205f63eda_o.gif",
    "id_album": "1746345504",
    "total": 5,
    "size_max_detail_page": 1,
    "list_detail": [
      {
        "index_page": 0,
        "link_page": "https://github.com/lmbstudiocontact/mb5_dt_alb_0/raw/main/14132021_dta_1746345504_index_0.json"
      }
    ]
  },
  {
    "title": "Naruto Anime_L2",
    "link_thumb": "https://live.staticflickr.com/65535/51786458632_f393d9c039_o.gif",
    "id_album": "1894397984",
    "total": 37,
    "size_max_detail_page": 1,
    "list_detail": [
      {
        "index_page": 0,
        "link_page": "https://github.com/lmbstudiocontact/mb5_dt_alb_0/raw/main/14132021_dta_1894397984_index_0.json"
      }
    ]
  },
  {
    "title": "Wolf_L5",
    "link_thumb": "https://live.staticflickr.com/65535/51787501263_05c3bf9a15_o.gif",
    "id_album": "-1110849962",
    "total": 5,
    "size_max_detail_page": 1,
    "list_detail": [
      {
        "index_page": 0,
        "link_page": "https://github.com/lmbstudiocontact/mb5_dt_alb_0/raw/main/14132021_dta_-1110849962_index_0.json"
      }
    ]
  },
  {
    "title": "Birds_L7",
    "link_thumb": "https://live.staticflickr.com/65535/51786400202_dd1c9eb59c_o.gif",
    "id_album": "1119566096",
    "total": 2,
    "size_max_detail_page": 1,
    "list_detail": [
      {
        "index_page": 0,
        "link_page": "https://github.com/lmbstudiocontact/mb5_dt_alb_0/raw/main/14132021_dta_1119566096_index_0.json"
      }
    ]
  },
  {
    "title": "One Punch Man Anime_L2",
    "link_thumb": "https://live.staticflickr.com/65535/51786470477_153fbd27ec_o.gif",
    "id_album": "-1626855613",
    "total": 2,
    "size_max_detail_page": 1,
    "list_detail": [
      {
        "index_page": 0,
        "link_page": "https://github.com/lmbstudiocontact/mb5_dt_alb_0/raw/main/14132021_dta_-1626855613_index_0.json"
      }
    ]
  },
  {
    "title": "Death Note Anime_L2",
    "link_thumb": "https://live.staticflickr.com/65535/51787201736_6051043540_o.gif",
    "id_album": "-374116173",
    "total": 8,
    "size_max_detail_page": 1,
    "list_detail": [
      {
        "index_page": 0,
        "link_page": "https://github.com/lmbstudiocontact/mb5_dt_alb_0/raw/main/14132021_dta_-374116173_index_0.json"
      }
    ]
  },
  {
    "title": "One Punch Man Anime_L4",
    "link_thumb": "https://live.staticflickr.com/65535/51787536588_79a6ffd8ae_o.gif",
    "id_album": "-1626855611",
    "total": 2,
    "size_max_detail_page": 1,
    "list_detail": [
      {
        "index_page": 0,
        "link_page": "https://github.com/lmbstudiocontact/mb5_dt_alb_0/raw/main/14132021_dta_-1626855611_index_0.json"
      }
    ]
  },
  {
    "title": "Death Note Anime_L1",
    "link_thumb": "https://live.staticflickr.com/65535/51786384747_232b5cca76_o.gif",
    "id_album": "-374116174",
    "total": 8,
    "size_max_detail_page": 1,
    "list_detail": [
      {
        "index_page": 0,
        "link_page": "https://github.com/lmbstudiocontact/mb5_dt_alb_0/raw/main/14132021_dta_-374116174_index_0.json"
      }
    ]
  },
  {
    "title": "Game",
    "link_thumb": "https://live.staticflickr.com/65535/51786407457_7eb5d8e2bf_o.gif",
    "id_album": "2211858",
    "total": 100,
    "size_max_detail_page": 2,
    "list_detail": [
      {
        "index_page": 0,
        "link_page": "https://github.com/lmbstudiocontact/mb5_dt_alb_0/raw/main/14132021_dta_2211858_index_0.json"
      },
      {
        "index_page": 1,
        "link_page": "https://github.com/lmbstudiocontact/mb5_dt_alb_0/raw/main/14132021_dta_2211858_index_1.json"
      }
    ]
  },
  {
    "title": "Animal Art_L1",
    "link_thumb": "https://live.staticflickr.com/65535/51787211721_c19b99148e_o.gif",
    "id_album": "97007461",
    "total": 7,
    "size_max_detail_page": 1,
    "list_detail": [
      {
        "index_page": 0,
        "link_page": "https://github.com/lmbstudiocontact/mb5_dt_alb_0/raw/main/14132021_dta_97007461_index_0.json"
      }
    ]
  },
  {
    "title": "Death Note Anime_L3",
    "link_thumb": "https://live.staticflickr.com/65535/51787200001_fba11932ac_o.gif",
    "id_album": "-374116172",
    "total": 8,
    "size_max_detail_page": 1,
    "list_detail": [
      {
        "index_page": 0,
        "link_page": "https://github.com/lmbstudiocontact/mb5_dt_alb_0/raw/main/14132021_dta_-374116172_index_0.json"
      }
    ]
  },
  {
    "title": "Panda_L7",
    "link_thumb": "https://live.staticflickr.com/65535/51786466677_d6b426895d_o.gif",
    "id_album": "1123959312",
    "total": 11,
    "size_max_detail_page": 1,
    "list_detail": [
      {
        "index_page": 0,
        "link_page": "https://github.com/lmbstudiocontact/mb5_dt_alb_0/raw/main/14132021_dta_1123959312_index_0.json"
      }
    ]
  },
  {
    "title": "Pooh_L7",
    "link_thumb": "https://live.staticflickr.com/65535/51788161255_dc5945ff35_o.gif",
    "id_album": "1269389010",
    "total": 9,
    "size_max_detail_page": 1,
    "list_detail": [
      {
        "index_page": 0,
        "link_page": "https://github.com/lmbstudiocontact/mb5_dt_alb_0/raw/main/14132021_dta_1269389010_index_0.json"
      }
    ]
  },
  {
    "title": "Raccoons_L5",
    "link_thumb": "https://live.staticflickr.com/65535/51787516558_69fcc6b24c_o.gif",
    "id_album": "1998705268",
    "total": 20,
    "size_max_detail_page": 1,
    "list_detail": [
      {
        "index_page": 0,
        "link_page": "https://github.com/lmbstudiocontact/mb5_dt_alb_0/raw/main/14132021_dta_1998705268_index_0.json"
      }
    ]
  },
  {
    "title": "Animal Art_L2",
    "link_thumb": "https://live.staticflickr.com/65535/51787211681_2c988c3447_o.gif",
    "id_album": "97007462",
    "total": 7,
    "size_max_detail_page": 1,
    "list_detail": [
      {
        "index_page": 0,
        "link_page": "https://github.com/lmbstudiocontact/mb5_dt_alb_0/raw/main/14132021_dta_97007462_index_0.json"
      }
    ]
  },
  {
    "title": "Cute Art_L5",
    "link_thumb": "https://live.staticflickr.com/65535/51787446333_a453804602_o.gif",
    "id_album": "-629963486",
    "total": 76,
    "size_max_detail_page": 2,
    "list_detail": [
      {
        "index_page": 0,
        "link_page": "https://github.com/lmbstudiocontact/mb5_dt_alb_0/raw/main/14132021_dta_-629963486_index_0.json"
      },
      {
        "index_page": 1,
        "link_page": "https://github.com/lmbstudiocontact/mb5_dt_alb_0/raw/main/14132021_dta_-629963486_index_1.json"
      }
    ]
  },
  {
    "title": "Kitty & My Melody_L2",
    "link_thumb": "https://live.staticflickr.com/65535/51788109825_692cb90d30_o.gif",
    "id_album": "-378480544",
    "total": 76,
    "size_max_detail_page": 2,
    "list_detail": [
      {
        "index_page": 0,
        "link_page": "https://github.com/lmbstudiocontact/mb5_dt_alb_0/raw/main/14132021_dta_-378480544_index_0.json"
      },
      {
        "index_page": 1,
        "link_page": "https://github.com/lmbstudiocontact/mb5_dt_alb_0/raw/main/14132021_dta_-378480544_index_1.json"
      }
    ]
  },
  {
    "title": "Animal Art_L3",
    "link_thumb": "https://live.staticflickr.com/65535/51787832149_46e328bd41_o.gif",
    "id_album": "97007463",
    "total": 7,
    "size_max_detail_page": 1,
    "list_detail": [
      {
        "index_page": 0,
        "link_page": "https://github.com/lmbstudiocontact/mb5_dt_alb_0/raw/main/14132021_dta_97007463_index_0.json"
      }
    ]
  },
  {
    "title": "Simpsons Cartoon_L1",
    "link_thumb": "https://live.staticflickr.com/65535/51787535748_3902e78572_o.gif",
    "id_album": "1276946588",
    "total": 8,
    "size_max_detail_page": 1,
    "list_detail": [
      {
        "index_page": 0,
        "link_page": "https://github.com/lmbstudiocontact/mb5_dt_alb_0/raw/main/14132021_dta_1276946588_index_0.json"
      }
    ]
  },
  {
    "title": "Madagascar Cartoon_L1",
    "link_thumb": "https://live.staticflickr.com/65535/51787281071_312830da41_o.gif",
    "id_album": "-2014542390",
    "total": 9,
    "size_max_detail_page": 1,
    "list_detail": [
      {
        "index_page": 0,
        "link_page": "https://github.com/lmbstudiocontact/mb5_dt_alb_0/raw/main/14132021_dta_-2014542390_index_0.json"
      }
    ]
  },
  {
    "title": "Boku No Hero Academia Anime_L4",
    "link_thumb": "https://live.staticflickr.com/65535/51787833439_f8a455db69_o.gif",
    "id_album": "197312542",
    "total": 19,
    "size_max_detail_page": 1,
    "list_detail": [
      {
        "index_page": 0,
        "link_page": "https://github.com/lmbstudiocontact/mb5_dt_alb_0/raw/main/14132021_dta_197312542_index_0.json"
      }
    ]
  },
  {
    "title": "Other_L7",
    "link_thumb": "https://live.staticflickr.com/65535/51787287706_7ed721623a_o.gif",
    "id_album": "-1106495206",
    "total": 57,
    "size_max_detail_page": 2,
    "list_detail": [
      {
        "index_page": 0,
        "link_page": "https://github.com/lmbstudiocontact/mb5_dt_alb_0/raw/main/14132021_dta_-1106495206_index_0.json"
      },
      {
        "index_page": 1,
        "link_page": "https://github.com/lmbstudiocontact/mb5_dt_alb_0/raw/main/14132021_dta_-1106495206_index_1.json"
      }
    ]
  },
  {
    "title": "Rio 2_L5",
    "link_thumb": "https://live.staticflickr.com/65535/51788149805_2b72b3409c_o.gif",
    "id_album": "-1210862914",
    "total": 17,
    "size_max_detail_page": 1,
    "list_detail": [
      {
        "index_page": 0,
        "link_page": "https://github.com/lmbstudiocontact/mb5_dt_alb_0/raw/main/14132021_dta_-1210862914_index_0.json"
      }
    ]
  },
  {
    "title": "Bear_L6",
    "link_thumb": "https://live.staticflickr.com/65535/51787199391_dd45a40f3e_o.gif",
    "id_album": "1430316469",
    "total": 70,
    "size_max_detail_page": 2,
    "list_detail": [
      {
        "index_page": 0,
        "link_page": "https://github.com/lmbstudiocontact/mb5_dt_alb_0/raw/main/14132021_dta_1430316469_index_0.json"
      },
      {
        "index_page": 1,
        "link_page": "https://github.com/lmbstudiocontact/mb5_dt_alb_0/raw/main/14132021_dta_1430316469_index_1.json"
      }
    ]
  },
  {
    "title": "Boss Baby Cartoon_L1",
    "link_thumb": "https://live.staticflickr.com/65535/51787827159_d52d6cabbb_o.gif",
    "id_album": "158762701",
    "total": 16,
    "size_max_detail_page": 1,
    "list_detail": [
      {
        "index_page": 0,
        "link_page": "https://github.com/lmbstudiocontact/mb5_dt_alb_0/raw/main/14132021_dta_158762701_index_0.json"
      }
    ]
  },
  {
    "title": "Ghibli Anime_L4",
    "link_thumb": "https://live.staticflickr.com/65535/51787866339_5ec707b984_o.gif",
    "id_album": "-749595044",
    "total": 17,
    "size_max_detail_page": 1,
    "list_detail": [
      {
        "index_page": 0,
        "link_page": "https://github.com/lmbstudiocontact/mb5_dt_alb_0/raw/main/14132021_dta_-749595044_index_0.json"
      }
    ]
  },
  {
    "title": "Boku No Hero Academia Anime_L5",
    "link_thumb": "https://live.staticflickr.com/65535/51787456668_66b8301e93_o.gif",
    "id_album": "197312543",
    "total": 19,
    "size_max_detail_page": 1,
    "list_detail": [
      {
        "index_page": 0,
        "link_page": "https://github.com/lmbstudiocontact/mb5_dt_alb_0/raw/main/14132021_dta_197312543_index_0.json"
      }
    ]
  },
  {
    "title": "Girl_L7",
    "link_thumb": "https://live.staticflickr.com/65535/51787856594_d52ac52abf_o.gif",
    "id_album": "1702905294",
    "total": 245,
    "size_max_detail_page": 5,
    "list_detail": [
      {
        "index_page": 0,
        "link_page": "https://github.com/lmbstudiocontact/mb5_dt_alb_0/raw/main/14132021_dta_1702905294_index_0.json"
      },
      {
        "index_page": 1,
        "link_page": "https://github.com/lmbstudiocontact/mb5_dt_alb_0/raw/main/14132021_dta_1702905294_index_1.json"
      },
      {
        "index_page": 2,
        "link_page": "https://github.com/lmbstudiocontact/mb5_dt_alb_0/raw/main/14132021_dta_1702905294_index_2.json"
      },
      {
        "index_page": 3,
        "link_page": "https://github.com/lmbstudiocontact/mb5_dt_alb_0/raw/main/14132021_dta_1702905294_index_3.json"
      },
      {
        "index_page": 4,
        "link_page": "https://github.com/lmbstudiocontact/mb5_dt_alb_0/raw/main/14132021_dta_1702905294_index_4.json"
      }
    ]
  },
  {
    "title": "Totoro_L6",
    "link_thumb": "https://live.staticflickr.com/65535/51786461702_176b1d28b2_o.gif",
    "id_album": "1833828886",
    "total": 41,
    "size_max_detail_page": 1,
    "list_detail": [
      {
        "index_page": 0,
        "link_page": "https://github.com/lmbstudiocontact/mb5_dt_alb_0/raw/main/14132021_dta_1833828886_index_0.json"
      }
    ]
  },
  {
    "title": "Disney Cartoon_L4",
    "link_thumb": "https://live.staticflickr.com/65535/51786377637_f5e5b7e9ea_o.gif",
    "id_album": "-779586267",
    "total": 54,
    "size_max_detail_page": 2,
    "list_detail": [
      {
        "index_page": 0,
        "link_page": "https://github.com/lmbstudiocontact/mb5_dt_alb_0/raw/main/14132021_dta_-779586267_index_0.json"
      },
      {
        "index_page": 1,
        "link_page": "https://github.com/lmbstudiocontact/mb5_dt_alb_0/raw/main/14132021_dta_-779586267_index_1.json"
      }
    ]
  },
  {
    "title": "Sheep_L7",
    "link_thumb": "https://live.staticflickr.com/65535/51787273771_ac4f0401a3_o.gif",
    "id_album": "-576277777",
    "total": 2,
    "size_max_detail_page": 1,
    "list_detail": [
      {
        "index_page": 0,
        "link_page": "https://github.com/lmbstudiocontact/mb5_dt_alb_0/raw/main/14132021_dta_-576277777_index_0.json"
      }
    ]
  },
  {
    "title": "Buddhist Terms_L1",
    "link_thumb": "https://live.staticflickr.com/65535/51787203691_b0f95a86f8_o.gif",
    "id_album": "518853928",
    "total": 13,
    "size_max_detail_page": 1,
    "list_detail": [
      {
        "index_page": 0,
        "link_page": "https://github.com/lmbstudiocontact/mb5_dt_alb_0/raw/main/14132021_dta_518853928_index_0.json"
      }
    ]
  },
  {
    "title": "Panda Art_L2",
    "link_thumb": "https://live.staticflickr.com/65535/51788153940_c69aaa2453_o.gif",
    "id_album": "586574344",
    "total": 5,
    "size_max_detail_page": 1,
    "list_detail": [
      {
        "index_page": 0,
        "link_page": "https://github.com/lmbstudiocontact/mb5_dt_alb_0/raw/main/14132021_dta_586574344_index_0.json"
      }
    ]
  },
  {
    "title": "Donald Duck Cartoon_L4",
    "link_thumb": "https://live.staticflickr.com/65535/51787204371_4fe168b377_o.gif",
    "id_album": "-1917621482",
    "total": 4,
    "size_max_detail_page": 1,
    "list_detail": [
      {
        "index_page": 0,
        "link_page": "https://github.com/lmbstudiocontact/mb5_dt_alb_0/raw/main/14132021_dta_-1917621482_index_0.json"
      }
    ]
  },
  {
    "title": "Detective Conan_L5",
    "link_thumb": "https://live.staticflickr.com/65535/51788092150_ec27c0fe84_o.gif",
    "id_album": "-1285383388",
    "total": 16,
    "size_max_detail_page": 1,
    "list_detail": [
      {
        "index_page": 0,
        "link_page": "https://github.com/lmbstudiocontact/mb5_dt_alb_0/raw/main/14132021_dta_-1285383388_index_0.json"
      }
    ]
  },
  {
    "title": "Smurf Houses Cartoon_L2",
    "link_thumb": "https://live.staticflickr.com/65535/51786456402_1fb303f0c7_o.gif",
    "id_album": "228264851",
    "total": 4,
    "size_max_detail_page": 1,
    "list_detail": [
      {
        "index_page": 0,
        "link_page": "https://github.com/lmbstudiocontact/mb5_dt_alb_0/raw/main/14132021_dta_228264851_index_0.json"
      }
    ]
  },
  {
    "title": "Disney Cartoon_L1",
    "link_thumb": "https://live.staticflickr.com/65535/51787466358_4da8a2e620_o.gif",
    "id_album": "-779586270",
    "total": 54,
    "size_max_detail_page": 2,
    "list_detail": [
      {
        "index_page": 0,
        "link_page": "https://github.com/lmbstudiocontact/mb5_dt_alb_0/raw/main/14132021_dta_-779586270_index_0.json"
      },
      {
        "index_page": 1,
        "link_page": "https://github.com/lmbstudiocontact/mb5_dt_alb_0/raw/main/14132021_dta_-779586270_index_1.json"
      }
    ]
  },
  {
    "title": "Monkey_L7",
    "link_thumb": "https://live.staticflickr.com/65535/51788160730_a7f2141678_o.gif",
    "id_album": "444828983",
    "total": 2,
    "size_max_detail_page": 1,
    "list_detail": [
      {
        "index_page": 0,
        "link_page": "https://github.com/lmbstudiocontact/mb5_dt_alb_0/raw/main/14132021_dta_444828983_index_0.json"
      }
    ]
  },
  {
    "title": "Plants Vs Zombies_L4",
    "link_thumb": "https://live.staticflickr.com/65535/51787541418_92f9f143db_o.gif",
    "id_album": "-1426777467",
    "total": 24,
    "size_max_detail_page": 1,
    "list_detail": [
      {
        "index_page": 0,
        "link_page": "https://github.com/lmbstudiocontact/mb5_dt_alb_0/raw/main/14132021_dta_-1426777467_index_0.json"
      }
    ]
  },
  {
    "title": "Pokmon Anime_L1",
    "link_thumb": "https://live.staticflickr.com/65535/51787506163_f02138fc9b_o.gif",
    "id_album": "-555824144",
    "total": 108,
    "size_max_detail_page": 3,
    "list_detail": [
      {
        "index_page": 0,
        "link_page": "https://github.com/lmbstudiocontact/mb5_dt_alb_0/raw/main/14132021_dta_-555824144_index_0.json"
      },
      {
        "index_page": 1,
        "link_page": "https://github.com/lmbstudiocontact/mb5_dt_alb_0/raw/main/14132021_dta_-555824144_index_1.json"
      },
      {
        "index_page": 2,
        "link_page": "https://github.com/lmbstudiocontact/mb5_dt_alb_0/raw/main/14132021_dta_-555824144_index_2.json"
      }
    ]
  },
  {
    "title": "Cat_L7",
    "link_thumb": "https://live.staticflickr.com/65535/51787829784_94525df105_o.gif",
    "id_album": "2011284116",
    "total": 105,
    "size_max_detail_page": 3,
    "list_detail": [
      {
        "index_page": 0,
        "link_page": "https://github.com/lmbstudiocontact/mb5_dt_alb_0/raw/main/14132021_dta_2011284116_index_0.json"
      },
      {
        "index_page": 1,
        "link_page": "https://github.com/lmbstudiocontact/mb5_dt_alb_0/raw/main/14132021_dta_2011284116_index_1.json"
      },
      {
        "index_page": 2,
        "link_page": "https://github.com/lmbstudiocontact/mb5_dt_alb_0/raw/main/14132021_dta_2011284116_index_2.json"
      }
    ]
  },
  {
    "title": "Rick and Morty Cartoon_Animation",
    "link_thumb": "https://live.staticflickr.com/65535/51787225501_913d799e6f_o.gif",
    "id_album": "-2048279842",
    "total": 1,
    "size_max_detail_page": 1,
    "list_detail": [
      {
        "index_page": 0,
        "link_page": "https://github.com/lmbstudiocontact/mb5_dt_alb_0/raw/main/14132021_dta_-2048279842_index_0.json"
      }
    ]
  },
  {
    "title": "Peace Art_L7",
    "link_thumb": "https://live.staticflickr.com/65535/51786450407_f96e8d8eb0_o.gif",
    "id_album": "437172985",
    "total": 34,
    "size_max_detail_page": 1,
    "list_detail": [
      {
        "index_page": 0,
        "link_page": "https://github.com/lmbstudiocontact/mb5_dt_alb_0/raw/main/14132021_dta_437172985_index_0.json"
      }
    ]
  },
  {
    "title": "Mickey Cartoon_L2",
    "link_thumb": "https://live.staticflickr.com/65535/51787513278_c9aed7ae5a_o.gif",
    "id_album": "1680949823",
    "total": 22,
    "size_max_detail_page": 1,
    "list_detail": [
      {
        "index_page": 0,
        "link_page": "https://github.com/lmbstudiocontact/mb5_dt_alb_0/raw/main/14132021_dta_1680949823_index_0.json"
      }
    ]
  },
  {
    "title": "Pokmon Anime_L5",
    "link_thumb": "https://live.staticflickr.com/65535/51787517038_4b2f8c2831_o.gif",
    "id_album": "-555824140",
    "total": 108,
    "size_max_detail_page": 3,
    "list_detail": [
      {
        "index_page": 0,
        "link_page": "https://github.com/lmbstudiocontact/mb5_dt_alb_0/raw/main/14132021_dta_-555824140_index_0.json"
      },
      {
        "index_page": 1,
        "link_page": "https://github.com/lmbstudiocontact/mb5_dt_alb_0/raw/main/14132021_dta_-555824140_index_1.json"
      },
      {
        "index_page": 2,
        "link_page": "https://github.com/lmbstudiocontact/mb5_dt_alb_0/raw/main/14132021_dta_-555824140_index_2.json"
      }
    ]
  },
  {
    "title": "Butterfly_L1",
    "link_thumb": "https://live.staticflickr.com/65535/51788065995_af44e88022_o.gif",
    "id_album": "657564369",
    "total": 6,
    "size_max_detail_page": 1,
    "list_detail": [
      {
        "index_page": 0,
        "link_page": "https://github.com/lmbstudiocontact/mb5_dt_alb_0/raw/main/14132021_dta_657564369_index_0.json"
      }
    ]
  }
]