[
  {
    "title": "Seven deadly sins Anime_L3",
    "link_thumb": "https://live.staticflickr.com/65535/51781188770_0f3f2d6161_n.jpg",
    "id_album": "1802210939",
    "total": 43,
    "size_max_detail_page": 1,
    "list_detail": [
      {
        "index_page": 0,
        "link_page": "https://github.com/lmbstudiocontact/mb5_dt_alb_0/raw/main/14132021_dta_1802210939_index_0.json"
      }
    ]
  },
  {
    "title": "Cute Art_L5",
    "link_thumb": "https://live.staticflickr.com/65535/51779333622_3000f7f715_o.gif",
    "id_album": "-629963486",
    "total": 76,
    "size_max_detail_page": 2,
    "list_detail": [
      {
        "index_page": 0,
        "link_page": "https://github.com/lmbstudiocontact/mb5_dt_alb_0/raw/main/14132021_dta_-629963486_index_0.json"
      },
      {
        "index_page": 1,
        "link_page": "https://github.com/lmbstudiocontact/mb5_dt_alb_0/raw/main/14132021_dta_-629963486_index_1.json"
      }
    ]
  },
  {
    "title": "Wolf_L4",
    "link_thumb": "https://live.staticflickr.com/65535/51704253578_cb44cca1d2_o.gif",
    "id_album": "-1110849963",
    "total": 5,
    "size_max_detail_page": 1,
    "list_detail": [
      {
        "index_page": 0,
        "link_page": "https://github.com/lmbstudiocontact/mb5_dt_alb_0/raw/main/14132021_dta_-1110849963_index_0.json"
      }
    ]
  },
  {
    "title": "Cute Art_L1",
    "link_thumb": "https://live.staticflickr.com/65535/51779359397_274810d503_o.gif",
    "id_album": "-629963490",
    "total": 76,
    "size_max_detail_page": 2,
    "list_detail": [
      {
        "index_page": 0,
        "link_page": "https://github.com/lmbstudiocontact/mb5_dt_alb_0/raw/main/14132021_dta_-629963490_index_0.json"
      },
      {
        "index_page": 1,
        "link_page": "https://github.com/lmbstudiocontact/mb5_dt_alb_0/raw/main/14132021_dta_-629963490_index_1.json"
      }
    ]
  },
  {
    "title": "Miku",
    "link_thumb": "https://live.staticflickr.com/65535/51694744964_261bffe88d_o.gif",
    "id_album": "2398246",
    "total": 5,
    "size_max_detail_page": 1,
    "list_detail": [
      {
        "index_page": 0,
        "link_page": "https://github.com/lmbstudiocontact/mb5_dt_alb_0/raw/main/14132021_dta_2398246_index_0.json"
      }
    ]
  },
  {
    "title": "Smurf Houses Cartoon_L2",
    "link_thumb": "https://live.staticflickr.com/65535/51779503442_ee1b6afe0c_n.jpg",
    "id_album": "228264851",
    "total": 4,
    "size_max_detail_page": 1,
    "list_detail": [
      {
        "index_page": 0,
        "link_page": "https://github.com/lmbstudiocontact/mb5_dt_alb_0/raw/main/14132021_dta_228264851_index_0.json"
      }
    ]
  },
  {
    "title": "Dog_L7",
    "link_thumb": "https://live.staticflickr.com/65535/51697667845_1629e1664e_o.gif",
    "id_album": "2052455278",
    "total": 28,
    "size_max_detail_page": 1,
    "list_detail": [
      {
        "index_page": 0,
        "link_page": "https://github.com/lmbstudiocontact/mb5_dt_alb_0/raw/main/14132021_dta_2052455278_index_0.json"
      }
    ]
  },
  {
    "title": "Angry Birds_L1",
    "link_thumb": "https://live.staticflickr.com/65535/51780187641_553bcfe5ed_o.gif",
    "id_album": "2112729289",
    "total": 26,
    "size_max_detail_page": 1,
    "list_detail": [
      {
        "index_page": 0,
        "link_page": "https://github.com/lmbstudiocontact/mb5_dt_alb_0/raw/main/14132021_dta_2112729289_index_0.json"
      }
    ]
  },
  {
    "title": "Monkey_L6",
    "link_thumb": "https://live.staticflickr.com/65535/51700775136_dcc6ed331f_o.gif",
    "id_album": "444828982",
    "total": 2,
    "size_max_detail_page": 1,
    "list_detail": [
      {
        "index_page": 0,
        "link_page": "https://github.com/lmbstudiocontact/mb5_dt_alb_0/raw/main/14132021_dta_444828982_index_0.json"
      }
    ]
  },
  {
    "title": "Dragon Art_L3",
    "link_thumb": "https://live.staticflickr.com/65535/51779351832_179c238966_o.gif",
    "id_album": "2059014000",
    "total": 13,
    "size_max_detail_page": 1,
    "list_detail": [
      {
        "index_page": 0,
        "link_page": "https://github.com/lmbstudiocontact/mb5_dt_alb_0/raw/main/14132021_dta_2059014000_index_0.json"
      }
    ]
  },
  {
    "title": "Milkmokka Fofo_L6",
    "link_thumb": "https://live.staticflickr.com/65535/51780509473_cd61a6f177_o.gif",
    "id_album": "-1232313349",
    "total": 29,
    "size_max_detail_page": 1,
    "list_detail": [
      {
        "index_page": 0,
        "link_page": "https://github.com/lmbstudiocontact/mb5_dt_alb_0/raw/main/14132021_dta_-1232313349_index_0.json"
      }
    ]
  },
  {
    "title": "Poke_L6",
    "link_thumb": "https://live.staticflickr.com/65535/51702657386_3620cb0ee4_o.gif",
    "id_album": "1265605552",
    "total": 32,
    "size_max_detail_page": 1,
    "list_detail": [
      {
        "index_page": 0,
        "link_page": "https://github.com/lmbstudiocontact/mb5_dt_alb_0/raw/main/14132021_dta_1265605552_index_0.json"
      }
    ]
  },
  {
    "title": "Music_L5",
    "link_thumb": "https://live.staticflickr.com/65535/51700102417_bcb03265e2_o.gif",
    "id_album": "908522979",
    "total": 24,
    "size_max_detail_page": 1,
    "list_detail": [
      {
        "index_page": 0,
        "link_page": "https://github.com/lmbstudiocontact/mb5_dt_alb_0/raw/main/14132021_dta_908522979_index_0.json"
      }
    ]
  },
  {
    "title": "Lilo & Stitch Cartoon_L5",
    "link_thumb": "https://live.staticflickr.com/65535/51780896844_85b9c5e531_o.gif",
    "id_album": "685543663",
    "total": 30,
    "size_max_detail_page": 1,
    "list_detail": [
      {
        "index_page": 0,
        "link_page": "https://github.com/lmbstudiocontact/mb5_dt_alb_0/raw/main/14132021_dta_685543663_index_0.json"
      }
    ]
  },
  {
    "title": "Plants Vs Zombies_L1",
    "link_thumb": "https://live.staticflickr.com/65535/51779452992_0d26702638_o.gif",
    "id_album": "-1426777470",
    "total": 24,
    "size_max_detail_page": 1,
    "list_detail": [
      {
        "index_page": 0,
        "link_page": "https://github.com/lmbstudiocontact/mb5_dt_alb_0/raw/main/14132021_dta_-1426777470_index_0.json"
      }
    ]
  },
  {
    "title": "Mouse Hamster_L7",
    "link_thumb": "https://live.staticflickr.com/65535/51780862849_19651bff8d_o.gif",
    "id_album": "-2138980861",
    "total": 18,
    "size_max_detail_page": 1,
    "list_detail": [
      {
        "index_page": 0,
        "link_page": "https://github.com/lmbstudiocontact/mb5_dt_alb_0/raw/main/14132021_dta_-2138980861_index_0.json"
      }
    ]
  },
  {
    "title": "Fox_L7",
    "link_thumb": "https://live.staticflickr.com/65535/51698717155_9b5a8841d8_o.gif",
    "id_album": "2110220027",
    "total": 7,
    "size_max_detail_page": 1,
    "list_detail": [
      {
        "index_page": 0,
        "link_page": "https://github.com/lmbstudiocontact/mb5_dt_alb_0/raw/main/14132021_dta_2110220027_index_0.json"
      }
    ]
  },
  {
    "title": "Star War_L1",
    "link_thumb": "https://live.staticflickr.com/65535/51781172340_fa1c49dbce_n.jpg",
    "id_album": "-1637191766",
    "total": 2,
    "size_max_detail_page": 1,
    "list_detail": [
      {
        "index_page": 0,
        "link_page": "https://github.com/lmbstudiocontact/mb5_dt_alb_0/raw/main/14132021_dta_-1637191766_index_0.json"
      }
    ]
  },
  {
    "title": "Panda Art_L5",
    "link_thumb": "https://live.staticflickr.com/65535/51780930734_92550c0166_o.gif",
    "id_album": "586574347",
    "total": 5,
    "size_max_detail_page": 1,
    "list_detail": [
      {
        "index_page": 0,
        "link_page": "https://github.com/lmbstudiocontact/mb5_dt_alb_0/raw/main/14132021_dta_586574347_index_0.json"
      }
    ]
  },
  {
    "title": "Shiv_L3",
    "link_thumb": "https://live.staticflickr.com/65535/51702851037_d615a55a17_o.gif",
    "id_album": "-568595356",
    "total": 32,
    "size_max_detail_page": 1,
    "list_detail": [
      {
        "index_page": 0,
        "link_page": "https://github.com/lmbstudiocontact/mb5_dt_alb_0/raw/main/14132021_dta_-568595356_index_0.json"
      }
    ]
  },
  {
    "title": "Shiv_L4",
    "link_thumb": "https://live.staticflickr.com/65535/51703955908_9a5ef7f40a_o.gif",
    "id_album": "-568595355",
    "total": 32,
    "size_max_detail_page": 1,
    "list_detail": [
      {
        "index_page": 0,
        "link_page": "https://github.com/lmbstudiocontact/mb5_dt_alb_0/raw/main/14132021_dta_-568595355_index_0.json"
      }
    ]
  },
  {
    "title": "Panda Art_L4",
    "link_thumb": "https://live.staticflickr.com/65535/51780932644_10c4d94348_o.gif",
    "id_album": "586574346",
    "total": 5,
    "size_max_detail_page": 1,
    "list_detail": [
      {
        "index_page": 0,
        "link_page": "https://github.com/lmbstudiocontact/mb5_dt_alb_0/raw/main/14132021_dta_586574346_index_0.json"
      }
    ]
  },
  {
    "title": "Pooh_L6",
    "link_thumb": "https://live.staticflickr.com/65535/51704134345_3a15c80ff6_o.gif",
    "id_album": "1269389009",
    "total": 9,
    "size_max_detail_page": 1,
    "list_detail": [
      {
        "index_page": 0,
        "link_page": "https://github.com/lmbstudiocontact/mb5_dt_alb_0/raw/main/14132021_dta_1269389009_index_0.json"
      }
    ]
  },
  {
    "title": "Fox Art_L2",
    "link_thumb": "https://live.staticflickr.com/65535/51780846734_c6cd4fa8e7_o.gif",
    "id_album": "-646110861",
    "total": 7,
    "size_max_detail_page": 1,
    "list_detail": [
      {
        "index_page": 0,
        "link_page": "https://github.com/lmbstudiocontact/mb5_dt_alb_0/raw/main/14132021_dta_-646110861_index_0.json"
      }
    ]
  },
  {
    "title": "Doraemon Anime_L3",
    "link_thumb": "https://live.staticflickr.com/65535/51779367072_1ae1cdcaf6_o.gif",
    "id_album": "405661393",
    "total": 16,
    "size_max_detail_page": 1,
    "list_detail": [
      {
        "index_page": 0,
        "link_page": "https://github.com/lmbstudiocontact/mb5_dt_alb_0/raw/main/14132021_dta_405661393_index_0.json"
      }
    ]
  },
  {
    "title": "One Piece Anime_L4",
    "link_thumb": "https://live.staticflickr.com/65535/51780242106_baf17a7d34_o.gif",
    "id_album": "1351456607",
    "total": 135,
    "size_max_detail_page": 3,
    "list_detail": [
      {
        "index_page": 0,
        "link_page": "https://github.com/lmbstudiocontact/mb5_dt_alb_0/raw/main/14132021_dta_1351456607_index_0.json"
      },
      {
        "index_page": 1,
        "link_page": "https://github.com/lmbstudiocontact/mb5_dt_alb_0/raw/main/14132021_dta_1351456607_index_1.json"
      },
      {
        "index_page": 2,
        "link_page": "https://github.com/lmbstudiocontact/mb5_dt_alb_0/raw/main/14132021_dta_1351456607_index_2.json"
      }
    ]
  },
  {
    "title": "Dragon Ball Anime_L5",
    "link_thumb": "https://live.staticflickr.com/65535/51780853199_e9f1809806_o.gif",
    "id_album": "1464725224",
    "total": 60,
    "size_max_detail_page": 2,
    "list_detail": [
      {
        "index_page": 0,
        "link_page": "https://github.com/lmbstudiocontact/mb5_dt_alb_0/raw/main/14132021_dta_1464725224_index_0.json"
      },
      {
        "index_page": 1,
        "link_page": "https://github.com/lmbstudiocontact/mb5_dt_alb_0/raw/main/14132021_dta_1464725224_index_1.json"
      }
    ]
  },
  {
    "title": "Rio 2_L3",
    "link_thumb": "https://live.staticflickr.com/65535/51781155450_e8d861a3da_n.jpg",
    "id_album": "-1210862916",
    "total": 17,
    "size_max_detail_page": 1,
    "list_detail": [
      {
        "index_page": 0,
        "link_page": "https://github.com/lmbstudiocontact/mb5_dt_alb_0/raw/main/14132021_dta_-1210862916_index_0.json"
      }
    ]
  },
  {
    "title": "Dragon Art_L4",
    "link_thumb": "https://live.staticflickr.com/65535/51780416293_03b9bf6ae2_o.gif",
    "id_album": "2059014001",
    "total": 13,
    "size_max_detail_page": 1,
    "list_detail": [
      {
        "index_page": 0,
        "link_page": "https://github.com/lmbstudiocontact/mb5_dt_alb_0/raw/main/14132021_dta_2059014001_index_0.json"
      }
    ]
  },
  {
    "title": "Mickey Cartoon_L2",
    "link_thumb": "https://live.staticflickr.com/65535/51780854049_8254228b38_o.gif",
    "id_album": "1680949823",
    "total": 22,
    "size_max_detail_page": 1,
    "list_detail": [
      {
        "index_page": 0,
        "link_page": "https://github.com/lmbstudiocontact/mb5_dt_alb_0/raw/main/14132021_dta_1680949823_index_0.json"
      }
    ]
  },
  {
    "title": "Donald Duck Cartoon_L5",
    "link_thumb": "https://live.staticflickr.com/65535/51779376507_27d2c0f202_o.gif",
    "id_album": "-1917621481",
    "total": 4,
    "size_max_detail_page": 1,
    "list_detail": [
      {
        "index_page": 0,
        "link_page": "https://github.com/lmbstudiocontact/mb5_dt_alb_0/raw/main/14132021_dta_-1917621481_index_0.json"
      }
    ]
  },
  {
    "title": "Spider Man Cartoon_L2",
    "link_thumb": "https://live.staticflickr.com/65535/51781190760_54db16785f_n.jpg",
    "id_album": "1735002392",
    "total": 16,
    "size_max_detail_page": 1,
    "list_detail": [
      {
        "index_page": 0,
        "link_page": "https://github.com/lmbstudiocontact/mb5_dt_alb_0/raw/main/14132021_dta_1735002392_index_0.json"
      }
    ]
  },
  {
    "title": "Couple_L5",
    "link_thumb": "https://live.staticflickr.com/65535/51696409684_fc67995ca1_o.gif",
    "id_album": "-888889816",
    "total": 24,
    "size_max_detail_page": 1,
    "list_detail": [
      {
        "index_page": 0,
        "link_page": "https://github.com/lmbstudiocontact/mb5_dt_alb_0/raw/main/14132021_dta_-888889816_index_0.json"
      }
    ]
  },
  {
    "title": "One Punch Man Anime_L4",
    "link_thumb": "https://live.staticflickr.com/65535/51781178230_3de1885f0a_o.gif",
    "id_album": "-1626855611",
    "total": 2,
    "size_max_detail_page": 1,
    "list_detail": [
      {
        "index_page": 0,
        "link_page": "https://github.com/lmbstudiocontact/mb5_dt_alb_0/raw/main/14132021_dta_-1626855611_index_0.json"
      }
    ]
  },
  {
    "title": "Plants Vs Zombies_L3",
    "link_thumb": "https://live.staticflickr.com/65535/51779440642_02c1004ed2_o.gif",
    "id_album": "-1426777468",
    "total": 24,
    "size_max_detail_page": 1,
    "list_detail": [
      {
        "index_page": 0,
        "link_page": "https://github.com/lmbstudiocontact/mb5_dt_alb_0/raw/main/14132021_dta_-1426777468_index_0.json"
      }
    ]
  },
  {
    "title": "Doraemon Anime_L4",
    "link_thumb": "https://live.staticflickr.com/65535/51779361452_b3ff6455cb_o.gif",
    "id_album": "405661394",
    "total": 16,
    "size_max_detail_page": 1,
    "list_detail": [
      {
        "index_page": 0,
        "link_page": "https://github.com/lmbstudiocontact/mb5_dt_alb_0/raw/main/14132021_dta_405661394_index_0.json"
      }
    ]
  },
  {
    "title": "Raccoons_L1",
    "link_thumb": "https://live.staticflickr.com/65535/51703256501_29e00c4fa2_o.gif",
    "id_album": "1998705264",
    "total": 20,
    "size_max_detail_page": 1,
    "list_detail": [
      {
        "index_page": 0,
        "link_page": "https://github.com/lmbstudiocontact/mb5_dt_alb_0/raw/main/14132021_dta_1998705264_index_0.json"
      }
    ]
  },
  {
    "title": "Butterfly_L4",
    "link_thumb": "https://live.staticflickr.com/65535/51696199260_013e69abc9_o.gif",
    "id_album": "657564372",
    "total": 6,
    "size_max_detail_page": 1,
    "list_detail": [
      {
        "index_page": 0,
        "link_page": "https://github.com/lmbstudiocontact/mb5_dt_alb_0/raw/main/14132021_dta_657564372_index_0.json"
      }
    ]
  },
  {
    "title": "Anime Chibi_L6",
    "link_thumb": "https://live.staticflickr.com/65535/51780791664_7a635e1575_o.gif",
    "id_album": "-1298448214",
    "total": 12,
    "size_max_detail_page": 1,
    "list_detail": [
      {
        "index_page": 0,
        "link_page": "https://github.com/lmbstudiocontact/mb5_dt_alb_0/raw/main/14132021_dta_-1298448214_index_0.json"
      }
    ]
  },
  {
    "title": "Simpsons Cartoon_L2",
    "link_thumb": "https://live.staticflickr.com/65535/51780576878_e5994cdbd8_n.jpg",
    "id_album": "1276946589",
    "total": 8,
    "size_max_detail_page": 1,
    "list_detail": [
      {
        "index_page": 0,
        "link_page": "https://github.com/lmbstudiocontact/mb5_dt_alb_0/raw/main/14132021_dta_1276946589_index_0.json"
      }
    ]
  },
  {
    "title": "Buddhist Terms_L4",
    "link_thumb": "https://live.staticflickr.com/65535/51781029280_61657e6ba1_o.gif",
    "id_album": "518853931",
    "total": 13,
    "size_max_detail_page": 1,
    "list_detail": [
      {
        "index_page": 0,
        "link_page": "https://github.com/lmbstudiocontact/mb5_dt_alb_0/raw/main/14132021_dta_518853931_index_0.json"
      }
    ]
  },
  {
    "title": "Halloween Ghost Witch_L1",
    "link_thumb": "https://live.staticflickr.com/65535/51779399787_5347fee290_o.gif",
    "id_album": "1746571233",
    "total": 49,
    "size_max_detail_page": 1,
    "list_detail": [
      {
        "index_page": 0,
        "link_page": "https://github.com/lmbstudiocontact/mb5_dt_alb_0/raw/main/14132021_dta_1746571233_index_0.json"
      }
    ]
  },
  {
    "title": "Simpsons Cartoon",
    "link_thumb": "https://live.staticflickr.com/65535/51694910745_f3356a2c71_o.gif",
    "id_album": "-1732735896",
    "total": 4,
    "size_max_detail_page": 1,
    "list_detail": [
      {
        "index_page": 0,
        "link_page": "https://github.com/lmbstudiocontact/mb5_dt_alb_0/raw/main/14132021_dta_-1732735896_index_0.json"
      }
    ]
  },
  {
    "title": "Madagascar Cartoon_L3",
    "link_thumb": "https://live.staticflickr.com/65535/51780868249_dab4f29555_o.gif",
    "id_album": "-2014542388",
    "total": 9,
    "size_max_detail_page": 1,
    "list_detail": [
      {
        "index_page": 0,
        "link_page": "https://github.com/lmbstudiocontact/mb5_dt_alb_0/raw/main/14132021_dta_-2014542388_index_0.json"
      }
    ]
  },
  {
    "title": "Buddhist Terms_L1",
    "link_thumb": "https://live.staticflickr.com/65535/51781039440_5f50a5a3f6_o.gif",
    "id_album": "518853928",
    "total": 13,
    "size_max_detail_page": 1,
    "list_detail": [
      {
        "index_page": 0,
        "link_page": "https://github.com/lmbstudiocontact/mb5_dt_alb_0/raw/main/14132021_dta_518853928_index_0.json"
      }
    ]
  },
  {
    "title": "Halloween Ghost Witch_L2",
    "link_thumb": "https://live.staticflickr.com/65535/51779380952_47c6414521_o.gif",
    "id_album": "1746571234",
    "total": 49,
    "size_max_detail_page": 1,
    "list_detail": [
      {
        "index_page": 0,
        "link_page": "https://github.com/lmbstudiocontact/mb5_dt_alb_0/raw/main/14132021_dta_1746571234_index_0.json"
      }
    ]
  },
  {
    "title": "Fox_L6",
    "link_thumb": "https://live.staticflickr.com/65535/51697021827_9208b13824_o.gif",
    "id_album": "2110220026",
    "total": 7,
    "size_max_detail_page": 1,
    "list_detail": [
      {
        "index_page": 0,
        "link_page": "https://github.com/lmbstudiocontact/mb5_dt_alb_0/raw/main/14132021_dta_2110220026_index_0.json"
      }
    ]
  },
  {
    "title": "Death Note Anime_L1",
    "link_thumb": "https://live.staticflickr.com/65535/51780814234_f7bf0a7866_o.gif",
    "id_album": "-374116174",
    "total": 8,
    "size_max_detail_page": 1,
    "list_detail": [
      {
        "index_page": 0,
        "link_page": "https://github.com/lmbstudiocontact/mb5_dt_alb_0/raw/main/14132021_dta_-374116174_index_0.json"
      }
    ]
  },
  {
    "title": "Kung Fu Panda_L1",
    "link_thumb": "https://live.staticflickr.com/65535/51780857119_b9557b9852_o.gif",
    "id_album": "1222783550",
    "total": 2,
    "size_max_detail_page": 1,
    "list_detail": [
      {
        "index_page": 0,
        "link_page": "https://github.com/lmbstudiocontact/mb5_dt_alb_0/raw/main/14132021_dta_1222783550_index_0.json"
      }
    ]
  },
  {
    "title": "Death Note Anime_L4",
    "link_thumb": "https://live.staticflickr.com/65535/51779350467_e4048203f0_o.gif",
    "id_album": "-374116171",
    "total": 8,
    "size_max_detail_page": 1,
    "list_detail": [
      {
        "index_page": 0,
        "link_page": "https://github.com/lmbstudiocontact/mb5_dt_alb_0/raw/main/14132021_dta_-374116171_index_0.json"
      }
    ]
  }
]