[
  {
    "title": "Mickey Cartoon_L3",
    "link_thumb": "https://live.staticflickr.com/65535/51780852024_e85603e705_o.gif",
    "id_album": "1680949824",
    "total": 22,
    "size_max_detail_page": 1,
    "list_detail": [
      {
        "index_page": 0,
        "link_page": "https://github.com/lmbstudiocontact/mb5_dt_alb_0/raw/main/14132021_dta_1680949824_index_0.json"
      }
    ]
  },
  {
    "title": "Poke_L7",
    "link_thumb": "https://live.staticflickr.com/65535/51703597525_c11224a606_o.gif",
    "id_album": "1265605553",
    "total": 44,
    "size_max_detail_page": 1,
    "list_detail": [
      {
        "index_page": 0,
        "link_page": "https://github.com/lmbstudiocontact/mb5_dt_alb_0/raw/main/14132021_dta_1265605553_index_0.json"
      }
    ]
  },
  {
    "title": "Lion_L6",
    "link_thumb": "https://live.staticflickr.com/65535/51699213617_fdec116ea2_o.gif",
    "id_album": "1842745421",
    "total": 3,
    "size_max_detail_page": 1,
    "list_detail": [
      {
        "index_page": 0,
        "link_page": "https://github.com/lmbstudiocontact/mb5_dt_alb_0/raw/main/14132021_dta_1842745421_index_0.json"
      }
    ]
  },
  {
    "title": "Lilo & Stitch Cartoon_L4",
    "link_thumb": "https://live.staticflickr.com/65535/51780902079_0636becf0f_o.gif",
    "id_album": "685543662",
    "total": 30,
    "size_max_detail_page": 1,
    "list_detail": [
      {
        "index_page": 0,
        "link_page": "https://github.com/lmbstudiocontact/mb5_dt_alb_0/raw/main/14132021_dta_685543662_index_0.json"
      }
    ]
  },
  {
    "title": "Little Monk_L6",
    "link_thumb": "https://live.staticflickr.com/65535/51780886234_76f14037fa_o.gif",
    "id_album": "213942176",
    "total": 17,
    "size_max_detail_page": 1,
    "list_detail": [
      {
        "index_page": 0,
        "link_page": "https://github.com/lmbstudiocontact/mb5_dt_alb_0/raw/main/14132021_dta_213942176_index_0.json"
      }
    ]
  },
  {
    "title": "Music_L1",
    "link_thumb": "https://live.staticflickr.com/65535/51701693715_207ae00a80_o.gif",
    "id_album": "908522975",
    "total": 24,
    "size_max_detail_page": 1,
    "list_detail": [
      {
        "index_page": 0,
        "link_page": "https://github.com/lmbstudiocontact/mb5_dt_alb_0/raw/main/14132021_dta_908522975_index_0.json"
      }
    ]
  },
  {
    "title": "Couple Art_L6",
    "link_thumb": "https://live.staticflickr.com/65535/51780778049_e7893f63fb_o.gif",
    "id_album": "1239230758",
    "total": 37,
    "size_max_detail_page": 1,
    "list_detail": [
      {
        "index_page": 0,
        "link_page": "https://github.com/lmbstudiocontact/mb5_dt_alb_0/raw/main/14132021_dta_1239230758_index_0.json"
      }
    ]
  },
  {
    "title": "Animals",
    "link_thumb": "https://live.staticflickr.com/65535/51694407278_aee5c2cb3d_o.gif",
    "id_album": "807717335",
    "total": 1,
    "size_max_detail_page": 1,
    "list_detail": [
      {
        "index_page": 0,
        "link_page": "https://github.com/lmbstudiocontact/mb5_dt_alb_0/raw/main/14132021_dta_807717335_index_0.json"
      }
    ]
  },
  {
    "title": "Animal Art_L3",
    "link_thumb": "https://live.staticflickr.com/65535/51781039165_c04276b40b_o.gif",
    "id_album": "97007463",
    "total": 7,
    "size_max_detail_page": 1,
    "list_detail": [
      {
        "index_page": 0,
        "link_page": "https://github.com/lmbstudiocontact/mb5_dt_alb_0/raw/main/14132021_dta_97007463_index_0.json"
      }
    ]
  }
]